cppcheck_suppressor/__init__.py
cppcheck_suppressor/__main__.py
cppcheck_suppressor/results.py
cppcheck_suppressor/suppressions.py
cppcheck_suppressor/data/cppcheck.xsd
cppcheck_suppressor-0.0.3.dist-info/licenses/LICENSE.md
cppcheck_suppressor-0.0.3.dist-info/METADATA
cppcheck_suppressor-0.0.3.dist-info/WHEEL
cppcheck_suppressor-0.0.3.dist-info/entry_points.txt
cppcheck_suppressor-0.0.3.dist-info/top_level.txt
cppcheck_suppressor-0.0.3.dist-info/RECORD
