Metadata-Version: 2.4
Name: cppcheck-suppressor
Version: 0.0.3
Summary: Tool to create suppression files for Cppcheck from its results.
Author-email: Bugproduction <bugproduction@outlook.com>
License-Expression: MIT
Project-URL: Repository, https://gitlab.com/bugproduction/cppcheck-suppressor.git
Keywords: Cppcheck,suppressions
License-File: LICENSE.md
Requires-Dist: xmlschema
Provides-Extra: dev
Requires-Dist: black; extra == "dev"
Requires-Dist: build; extra == "dev"
Requires-Dist: pylint; extra == "dev"
Requires-Dist: pytest; extra == "dev"
Requires-Dist: pytest-cov; extra == "dev"
Requires-Dist: setuptools; extra == "dev"
Requires-Dist: twine; extra == "dev"
Dynamic: license-file
